pyrekordbox/__init__.py
pyrekordbox/__main__.py
pyrekordbox/_version.py
pyrekordbox/config.py
pyrekordbox/logger.py
pyrekordbox/rbxml.py
pyrekordbox/utils.py
pyrekordbox/anlz/__init__.py
pyrekordbox/anlz/file.py
pyrekordbox/anlz/structs.py
pyrekordbox/anlz/tags.py
pyrekordbox/db6/__init__.py
pyrekordbox/db6/aux_files.py
pyrekordbox/db6/database.py
pyrekordbox/db6/registry.py
pyrekordbox/db6/smartlist.py
pyrekordbox/db6/tables.py
pyrekordbox/mysettings/__init__.py
pyrekordbox/mysettings/file.py
pyrekordbox/mysettings/structs.py
pyrekordbox-0.4.4.dist-info/licenses/LICENSE
pyrekordbox-0.4.4.dist-info/METADATA
pyrekordbox-0.4.4.dist-info/WHEEL
pyrekordbox-0.4.4.dist-info/top_level.txt
pyrekordbox-0.4.4.dist-info/RECORD
