Metadata-Version: 2.4
Name: pyrekordbox
Version: 0.4.4
Summary: Inofficial Python package for interacting with the library of Pioneers Rekordbox DJ software.
Author-email: Dylan Jones <dylanljones94@gmail.com>
License: MIT License
Project-URL: Source, https://github.com/dylanljones/pyrekordbox
Project-URL: Documentation, https://pyrekordbox.readthedocs.io/en/stable/
Project-URL: Tracker, https://github.com/dylanljones/pyrekordbox/issues
Platform: any
Classifier: Development Status :: 4 - Beta
Classifier: Intended Audience :: Developers
Classifier: Intended Audience :: Information Technology
Classifier: License :: OSI Approved :: MIT License
Classifier: Natural Language :: English
Classifier: Operating System :: MacOS
Classifier: Operating System :: Microsoft :: Windows
Classifier: Programming Language :: Python :: 3
Classifier: Programming Language :: Python :: 3 :: Only
Classifier: Programming Language :: Python :: 3.8
Classifier: Programming Language :: Python :: 3.9
Classifier: Programming Language :: Python :: 3.10
Classifier: Programming Language :: Python :: 3.11
Classifier: Programming Language :: Python :: 3.12
Classifier: Topic :: Multimedia :: Sound/Audio
Requires-Python: >=3.8
License-File: LICENSE
Requires-Dist: bidict>=0.21.0
Requires-Dist: construct>=2.10.0
Requires-Dist: numpy>=1.19.0
Requires-Dist: packaging
Requires-Dist: psutil>=5.9.0
Requires-Dist: sqlalchemy>=2.0.0
Requires-Dist: sqlcipher3-wheels
Requires-Dist: python-dateutil
Provides-Extra: test
Requires-Dist: hypothesis>=6.0.0; extra == "test"
Requires-Dist: pytest>=6.2.0; extra == "test"
Requires-Dist: pytest-cov; extra == "test"
Dynamic: license-file
